odoo/addons/edi_stock_oca/README.rst
odoo/addons/edi_stock_oca/__init__.py
odoo/addons/edi_stock_oca/__manifest__.py
odoo/addons/edi_stock_oca/i18n/edi_stock_oca.pot
odoo/addons/edi_stock_oca/models/__init__.py
odoo/addons/edi_stock_oca/models/stock_picking.py
odoo/addons/edi_stock_oca/readme/CONTRIBUTORS.rst
odoo/addons/edi_stock_oca/readme/DESCRIPTION.rst
odoo/addons/edi_stock_oca/static/description/icon.png
odoo/addons/edi_stock_oca/static/description/index.html
odoo/addons/edi_stock_oca/tests/__init__.py
odoo/addons/edi_stock_oca/tests/test_edi.py
odoo/addons/edi_stock_oca/views/edi_exchange_record_views.xml
odoo/addons/edi_stock_oca/views/res_partner.xml
odoo/addons/edi_stock_oca/views/stock_picking.xml
odoo13_addon_edi_stock_oca-13.0.1.1.0.dist-info/METADATA
odoo13_addon_edi_stock_oca-13.0.1.1.0.dist-info/WHEEL
odoo13_addon_edi_stock_oca-13.0.1.1.0.dist-info/top_level.txt
odoo13_addon_edi_stock_oca-13.0.1.1.0.dist-info/RECORD
